odoo/addons/l10n_br_delivery_nfe/README.rst
odoo/addons/l10n_br_delivery_nfe/__init__.py
odoo/addons/l10n_br_delivery_nfe/__manifest__.py
odoo/addons/l10n_br_delivery_nfe/i18n/l10n_br_delivery_nfe.pot
odoo/addons/l10n_br_delivery_nfe/i18n/pt_BR.po
odoo/addons/l10n_br_delivery_nfe/models/__init__.py
odoo/addons/l10n_br_delivery_nfe/models/document.py
odoo/addons/l10n_br_delivery_nfe/models/product_product.py
odoo/addons/l10n_br_delivery_nfe/models/product_template.py
odoo/addons/l10n_br_delivery_nfe/models/stock_picking.py
odoo/addons/l10n_br_delivery_nfe/models/stock_picking_lacres.py
odoo/addons/l10n_br_delivery_nfe/models/stock_picking_vol.py
odoo/addons/l10n_br_delivery_nfe/security/ir.model.access.csv
odoo/addons/l10n_br_delivery_nfe/static/description/icon.png
odoo/addons/l10n_br_delivery_nfe/static/description/index.html
odoo/addons/l10n_br_delivery_nfe/tests/__init__.py
odoo/addons/l10n_br_delivery_nfe/tests/test_delivery_nfe.py
odoo/addons/l10n_br_delivery_nfe/tests/test_delivery_nfe_grouped.py
odoo/addons/l10n_br_delivery_nfe/views/nfe_document_view.xml
odoo/addons/l10n_br_delivery_nfe/views/product_product_view.xml
odoo/addons/l10n_br_delivery_nfe/views/product_template_view.xml
odoo/addons/l10n_br_delivery_nfe/views/stock_picking_view.xml
odoo/addons/l10n_br_delivery_nfe/wizards/__init__.py
odoo/addons/l10n_br_delivery_nfe/wizards/stock_generate_volumes.py
odoo/addons/l10n_br_delivery_nfe/wizards/stock_generate_volumes_view.xml
odoo/addons/l10n_br_delivery_nfe/wizards/stock_invoice_onshipping.py
odoo/addons/l10n_br_delivery_nfe/wizards/stock_invoice_onshipping_view.xml
odoo/addons/l10n_br_delivery_nfe/wizards/vol_stock_invoice_onshipping.py
odoo_addon_l10n_br_delivery_nfe-16.0.2.0.0.dist-info/METADATA
odoo_addon_l10n_br_delivery_nfe-16.0.2.0.0.dist-info/WHEEL
odoo_addon_l10n_br_delivery_nfe-16.0.2.0.0.dist-info/top_level.txt
odoo_addon_l10n_br_delivery_nfe-16.0.2.0.0.dist-info/RECORD
